pykinml/aev.py
pykinml/daev.py
pykinml/data.py
pykinml/hdf5_handler.py
pykinml/model_calculator.py
pykinml/multi_fid_loop.py
pykinml/nnpes.py
pykinml/prepper.py
pykinml/rdb.py
pykinml/trainer.py
pykinml-1.1.2.dist-info/LICENSE
pykinml-1.1.2.dist-info/METADATA
pykinml-1.1.2.dist-info/WHEEL
pykinml-1.1.2.dist-info/top_level.txt
pykinml-1.1.2.dist-info/RECORD
