Metadata-Version: 2.1
Name: pykinml
Version: 1.1.2
Summary: Neural Net Potential Energy Surface
Author-email: cjdever <cjdever@sandia.gov>, cmartia <cmartia@sandia.gov>, Judit Zádor <jzador@sandia.gov>, Habib Najm <hnnajm@sandia.gov>
Maintainer-email: cjdever <cjdever@sandia.gov>
License: Copyright 2024 National Technology & Engineering Solutions of Sandia, LLC (NTESS). 
Project-URL: homepage, https://github.com/sandialabs/pykinml
Project-URL: documentation, https://github.com/sandialabs/pykinml/wiki
Classifier: Environment :: Console
Classifier: Intended Audience :: Science/Research
Classifier: Natural Language :: English
Classifier: License :: OSI Approved :: BSD License
Classifier: Operating System :: OS Independent
Classifier: Programming Language :: Python :: 3.8
Classifier: Programming Language :: Python :: 3.9
Classifier: Programming Language :: Python :: 3.10
Classifier: Topic :: Scientific/Engineering :: Chemistry
Requires-Python: >=3.8
License-File: LICENSE
Requires-Dist: numpy (>=1.17.0)
Requires-Dist: ase (>=3.19)
Requires-Dist: h5py (>=3.7.0)
Requires-Dist: pandas
Requires-Dist: aevmod
Provides-Extra: plot
